 [
    {"name": "Jeopardy Code", "value": "jeopardy-code-lookup-response"},
    {"name": "Rework Code", "value": "rework-code-lookup-response"},
    {"name": "Carrier Name", "value": "carrier-name-lookup-response"},
    {"name": "Cancel Reason", "value": "cancel-reason-lookup-response"},
    {"name": "Desire Workorder Type", "value": "desire-workorder-type-lookup-response"},
    {"name": "Backhual Product", "value": "backhaul-product-lookup-response"},
    {"name": "Special Application", "value": "special-application-lookup-response"},
    {"name": "Priority Project", "value": "priority-project-lookup-response"},
    {"name": "Term", "value": "term-lookup-response"}
]